pepperpy_ai/__init__.py
pepperpy_ai/agents/__init__.py
pepperpy_ai/agents/analysis.py
pepperpy_ai/agents/architect.py
pepperpy_ai/agents/base.py
pepperpy_ai/agents/config.py
pepperpy_ai/agents/development.py
pepperpy_ai/agents/factory.py
pepperpy_ai/agents/interfaces.py
pepperpy_ai/agents/management.py
pepperpy_ai/agents/project_manager.py
pepperpy_ai/agents/qa.py
pepperpy_ai/agents/quality.py
pepperpy_ai/agents/research.py
pepperpy_ai/agents/researcher.py
pepperpy_ai/agents/review.py
pepperpy_ai/agents/reviewer.py
pepperpy_ai/agents/specialized.py
pepperpy_ai/agents/team.py
pepperpy_ai/agents/team_types.py
pepperpy_ai/agents/types.py
pepperpy_ai/ai_types.py
pepperpy_ai/base/message.py
pepperpy_ai/base/module.py
pepperpy_ai/base.py
pepperpy_ai/capabilities/__init__.py
pepperpy_ai/capabilities/base.py
pepperpy_ai/capabilities/chat/base.py
pepperpy_ai/capabilities/chat/config.py
pepperpy_ai/capabilities/chat/simple.py
pepperpy_ai/capabilities/chat/types.py
pepperpy_ai/capabilities/config.py
pepperpy_ai/capabilities/embeddings/base.py
pepperpy_ai/capabilities/embeddings/config.py
pepperpy_ai/capabilities/embeddings/simple.py
pepperpy_ai/capabilities/embeddings/types.py
pepperpy_ai/capabilities/rag/__init__.py
pepperpy_ai/capabilities/rag/base.py
pepperpy_ai/capabilities/rag/config.py
pepperpy_ai/capabilities/rag/document.py
pepperpy_ai/capabilities/rag/simple.py
pepperpy_ai/capabilities/rag/strategies/__init__.py
pepperpy_ai/capabilities/rag/strategies/base.py
pepperpy_ai/capabilities/rag/strategies/semantic.py
pepperpy_ai/capabilities/rag/types.py
pepperpy_ai/chat/__init__.py
pepperpy_ai/chat/config.py
pepperpy_ai/chat/conversation.py
pepperpy_ai/chat/types.py
pepperpy_ai/cli/__init__.py
pepperpy_ai/cli/deps.py
pepperpy_ai/config/__init__.py
pepperpy_ai/config/agent.py
pepperpy_ai/config/base.py
pepperpy_ai/config/capability.py
pepperpy_ai/config/chat.py
pepperpy_ai/config/client.py
pepperpy_ai/config/core.py
pepperpy_ai/config/embeddings.py
pepperpy_ai/config/llm.py
pepperpy_ai-0.2.1.dist-info/LICENSE
pepperpy_ai-0.2.1.dist-info/METADATA
pepperpy_ai-0.2.1.dist-info/WHEEL
pepperpy_ai-0.2.1.dist-info/entry_points.txt
pepperpy_ai-0.2.1.dist-info/RECORD
