Metadata-Version: 2.3
Name: pepperpy-ai
Version: 0.2.1
Summary: A flexible AI library with modular provider support
License: MIT
Keywords: ai,llm,nlp,machine-learning
Author: Felipe Pimentel
Author-email: felipe@pepperpy.ai
Requires-Python: >=3.12,<4.0
Classifier: Development Status :: 4 - Beta
Classifier: Intended Audience :: Developers
Classifier: License :: OSI Approved :: MIT License
Classifier: Programming Language :: Python :: 3
Classifier: Programming Language :: Python :: 3.12
Classifier: Programming Language :: Python :: 3.13
Classifier: Topic :: Scientific/Engineering :: Artificial Intelligence
Provides-Extra: all-capabilities
Provides-Extra: all-providers
Provides-Extra: anthropic
Provides-Extra: complete
Provides-Extra: openai
Provides-Extra: rag
Requires-Dist: aiohttp (>=3.11.11,<4.0.0)
Requires-Dist: anthropic (==0.42.0) ; extra == "anthropic" or extra == "all-providers" or extra == "complete"
Requires-Dist: async-generator (>=1.10,<2.0)
Requires-Dist: click (>=8.1.8,<9.0.0)
Requires-Dist: numpy (==2.2.1) ; extra == "rag" or extra == "all-capabilities" or extra == "complete"
Requires-Dist: openai (==1.59.7) ; extra == "openai" or extra == "all-providers" or extra == "complete"
Requires-Dist: pepperpy-core
Requires-Dist: python-dotenv (>=1.0.1,<2.0.0)
Requires-Dist: requests (>=2.32.3,<3.0.0)
Requires-Dist: sentence-transformers (==3.3.1) ; extra == "rag" or extra == "all-capabilities" or extra == "complete"
Project-URL: Documentation, https://docs.pepperpy.ai
Project-URL: Repository, https://github.com/pimentel/pepperpy-ai
